{"sections":{"cms-services":{"type":"cms-services","blocks":{"1614071790f5f451ac-0":{"type":"s_text","settings":{"service_icon":"shopify:\/\/shop_images\/1.png","title":"Security Policy","desc":"All Payment Are Secured"}},"1614071790f5f451ac-1":{"type":"s_text","settings":{"service_icon":"shopify:\/\/shop_images\/2.png","title":"Delivery Policy","desc":"On Worldwide"}},"1614071790f5f451ac-2":{"type":"s_text","settings":{"service_icon":"shopify:\/\/shop_images\/3.png","title":"Return Policy","desc":"30 Days Money Back Guarantee"}}},"block_order":["1614071790f5f451ac-0","1614071790f5f451ac-1","1614071790f5f451ac-2"],"settings":{"display_offer":true,"offer_bg":"#ffcc00","offer_img":"shopify:\/\/shop_images\/icon.png","offer_text_color":"#ffffff","offer_text":"WAREHOUSE EXCLUSIVE OFFERS","bg_color":"rgba(0,0,0,0)","title_color":"#ffdd00","title_hover_color":"#ffdd00","desc_color":"#ffffff","icon_color":"#ffffff","icon_hover_color":"#ffdd00"}},"slideshow":{"type":"slideshow","blocks":{"1580215063672-0":{"type":"image","settings":{"image":"shopify:\/\/shop_images\/slider-01.jpg","image_link":"#","show_video":false,"video_url":"https:\/\/www.youtube.com\/watch?v=XNCAFq1mOC4","title":"Headset Hyper X Cloud","sub_title":"First Time on Megashop Store Sale!","btn_txt":"Shop Now","btn_link":"#","title_color":"#ffffff","subtitle_color":"#ffffff","btn_bg_color":"#ffcc00","btn_txt_color":"#111111","btn_border_color":"#ffffff","btn_hovertxt_color":"#111111","text_position":"right","text_effect":"right"}},"1580215063672-1":{"type":"image","settings":{"image":"shopify:\/\/shop_images\/slider-02.jpg","image_link":"#","show_video":false,"video_url":"","title":"Xiaomi Mi A1 New Smart Phone","sub_title":"First Time on Megashop Store Sale!","btn_txt":"Shop Now","btn_link":"#","title_color":"#ffffff","subtitle_color":"#ffffff","btn_bg_color":"#ffcc00","btn_txt_color":"#111111","btn_border_color":"#ffffff","btn_hovertxt_color":"#111111","text_position":"left","text_effect":"left"}}},"block_order":["1580215063672-0","1580215063672-1"],"settings":{"slider_animation_type":"fade","slide_button_txt_color":"#ffffff","slide_button_txt_hover_color":"#ffcc00"}},"top-category":{"type":"top-category","blocks":{"6c1d3cc6-0685-45f1-bf01-66c37aacadb0":{"type":"text","settings":{"topcat_url":"shopify:\/\/products\/amber-square-air-shirt","service_icon":"shopify:\/\/shop_images\/01.png","title":"Apparel & Fashion","tt_mn_show_sub":true,"tt_sub_menu_clinklist":"footer-menu-2"}},"9b81100d-ce10-44d8-ab06-ad0fbff91ce9":{"type":"text","settings":{"topcat_url":"shopify:\/\/products\/eye-drops-gouttes-oculaires-lubricating-ophthalmic-solution","service_icon":"shopify:\/\/shop_images\/Baby-_-Child-Care.png","title":"Baby & Child Care","tt_mn_show_sub":false,"tt_sub_menu_clinklist":""}},"d0cc25b8-deae-4caf-bef5-07a13d26c30e":{"type":"text","settings":{"topcat_url":"shopify:\/\/products\/fresh-organics-red-onion","service_icon":"shopify:\/\/shop_images\/Diet-_-Nutrition.png","title":"Diet & Nutrition","tt_mn_show_sub":false,"tt_sub_menu_clinklist":""}},"f3a3d0c8-c0a8-4981-ad71-22af75662f7b":{"type":"text","settings":{"topcat_url":"shopify:\/\/products\/bang-olufsen-beoplay-h4-2nd-gen-wireless-over-ear-headphone","service_icon":"shopify:\/\/shop_images\/Gifts-_-Specialty.png","title":"Gifts & Specialty","tt_mn_show_sub":false,"tt_sub_menu_clinklist":""}},"373ec640-899c-4aa6-80cf-0e01be1a64f5":{"type":"text","settings":{"topcat_url":"shopify:\/\/products\/domestic-gourmet-automatic-espresso-coffee-capsule-machine","service_icon":"shopify:\/\/shop_images\/Home_Electronics.png","title":"Home & Electronics","tt_mn_show_sub":false,"tt_sub_menu_clinklist":""}},"8d98320a-816b-4ec1-8d3d-f5865fd118db":{"type":"text","settings":{"topcat_url":"shopify:\/\/products\/ellen-dining-chair","service_icon":"shopify:\/\/shop_images\/Household-Items.png","title":"Household Items","tt_mn_show_sub":false,"tt_sub_menu_clinklist":""}},"4319a167-cc23-4b12-9530-d3de96a790fa":{"type":"text","settings":{"topcat_url":"shopify:\/\/products\/french-door-refrigerator-in-fingerprint-resistant-stainless-steel","service_icon":"shopify:\/\/shop_images\/Vehicles-_-Accessories.png","title":"Vehicles & Accessories","tt_mn_show_sub":false,"tt_sub_menu_clinklist":""}},"eb56fb3e-e7be-4083-ae46-406c34513c88":{"type":"text","settings":{"topcat_url":"shopify:\/\/collections\/all","service_icon":"shopify:\/\/shop_images\/Other-Departments.png","title":"Other Departments","tt_mn_show_sub":false,"tt_sub_menu_clinklist":""}}},"block_order":["6c1d3cc6-0685-45f1-bf01-66c37aacadb0","9b81100d-ce10-44d8-ab06-ad0fbff91ce9","d0cc25b8-deae-4caf-bef5-07a13d26c30e","f3a3d0c8-c0a8-4981-ad71-22af75662f7b","373ec640-899c-4aa6-80cf-0e01be1a64f5","8d98320a-816b-4ec1-8d3d-f5865fd118db","4319a167-cc23-4b12-9530-d3de96a790fa","eb56fb3e-e7be-4083-ae46-406c34513c88"],"settings":{"bg_color":"#ffffff","title_color":"#111111","title_hover_color":"#2453c9","more_menu_category":"3","display_barcode":false,"bar_title":"Enjoy Convevient Order Tracking","bar_title_clr":"#333333","bar_desc":"Scan To Download App","bar_desc_clr":"#666666"}},"tt-topoffer":{"type":"tt-topoffer","blocks":{"282ba84b-fd64-41ea-a2db-689e57c37381":{"type":"offer_text","settings":{"topoffer_img_url":"#","topoffer_img":"shopify:\/\/shop_images\/cms-offer-01.jpg"}},"df70aabc-342d-4c1c-b56e-2f72a5e2a0b2":{"type":"offer_text","settings":{"topoffer_img_url":"#","topoffer_img":"shopify:\/\/shop_images\/cms-offer-02.jpg"}},"98858afd-4893-43ec-b48e-6a1cf2ad4fff":{"type":"offer_text","settings":{"topoffer_img_url":"#","topoffer_img":"shopify:\/\/shop_images\/cms-offer-03.jpg"}}},"block_order":["282ba84b-fd64-41ea-a2db-689e57c37381","df70aabc-342d-4c1c-b56e-2f72a5e2a0b2","98858afd-4893-43ec-b48e-6a1cf2ad4fff"],"settings":{"offer_bg":"#ffffff","offer_content":"End Of Year Sale 2022","offer_content_color":"#ffffff","offer_content_bgcolor":"#3f41bc"}},"special-product":{"type":"special-product","settings":{"class":"specialproduct","bg_color":"#ffffff","title":"Deals of the Day","subtitle":"Black Friday Sale","btn_url":"shopify:\/\/collections\/fashion","btn_txt":"View All","button_text_color":"#7b818f","button_hover_text_color":"#222222","collection":"special-electronics","product_col":"6"}},"category-feature":{"type":"category-feature","blocks":{"1622714104fc54d870-0":{"type":"text_collection","settings":{"image_1":"shopify:\/\/shop_images\/electronics-bg.jpg","collection_title":"Electronic & Gadgets","collection_cat_id":"electronics","sub_image_1":"shopify:\/\/shop_images\/headphone.png","sub_collection_title_1":"Headphone","sub_collection_cat_id_1":"speaker","sub_image_2":"shopify:\/\/shop_images\/laptop.png","sub_collection_title_2":"Laptop","sub_collection_cat_id_2":"laptop","sub_image_3":"shopify:\/\/shop_images\/mobile.png","sub_collection_title_3":"Mobile","sub_collection_cat_id_3":"mobile","sub_image_4":"shopify:\/\/shop_images\/speaker.png","sub_collection_title_4":"Speaker","sub_collection_cat_id_4":"speaker"}},"1d0c01a2-d68a-4089-b7a9-024ee2f38fd5":{"type":"text_collection","settings":{"image_1":"shopify:\/\/shop_images\/fashion-bg.jpg","collection_title":"Fashion & Clothes","collection_cat_id":"laptop","sub_image_1":"shopify:\/\/shop_images\/clothes.png","sub_collection_title_1":"Clothes","sub_collection_cat_id_1":"","sub_image_2":"shopify:\/\/shop_images\/jewelry.png","sub_collection_title_2":"Jewelry","sub_collection_cat_id_2":"","sub_image_3":"shopify:\/\/shop_images\/shoes.png","sub_collection_title_3":"Shoes","sub_collection_cat_id_3":"","sub_image_4":"shopify:\/\/shop_images\/watches.png","sub_collection_title_4":"Watches","sub_collection_cat_id_4":""}},"d1b19b99-2fa5-44ac-8cbd-7bd64ea75ab5":{"type":"text_collection","settings":{"image_1":"shopify:\/\/shop_images\/furniture-bg.jpg","collection_title":"Home & Kitchen","collection_cat_id":"electronics1","sub_image_1":"shopify:\/\/shop_images\/decor.png","sub_collection_title_1":"Decor","sub_collection_cat_id_1":"","sub_image_2":"shopify:\/\/shop_images\/furniture.png","sub_collection_title_2":"Furniture","sub_collection_cat_id_2":"","sub_image_3":"shopify:\/\/shop_images\/kichen.png","sub_collection_title_3":"Kitchen","sub_collection_cat_id_3":"","sub_image_4":"shopify:\/\/shop_images\/lighting.png","sub_collection_title_4":"Lighting","sub_collection_cat_id_4":""}}},"block_order":["1622714104fc54d870-0","1d0c01a2-d68a-4089-b7a9-024ee2f38fd5","d1b19b99-2fa5-44ac-8cbd-7bd64ea75ab5"],"settings":{"title":"Shop By Categories","subtitle":"Over 100+ Styles","banner_img":"shopify:\/\/shop_images\/banner-06.jpg","banner_url":"#","banner_title":"Home Beoplay A9 Tone","banner_title_color":"#ffffff","banner_subtitle":"Starts at,","banner_subtitle_color":"#ffffff","banner_desc":"$38.99","banner_desc_color":"#ffffff","image_content_bg_color":"#ffffff","title_color":"#111111","sub_title_color":"#111111","sub_bg_title_color":"#f5f5f5","sub_title_hv_color":"#ffffff","sub_bg_title_hv_color":"#2453c9"}},"our_brand":{"type":"our_brand","blocks":{"1605783755d6d9f598-0":{"type":"brand_image","settings":{"image":"shopify:\/\/shop_images\/01_00038628-66e8-43eb-af83-a2f5ca94cf00.png","link":"#"}},"1605783755d6d9f598-1":{"type":"brand_image","settings":{"image":"shopify:\/\/shop_images\/02.png","link":"#"}},"1605783755d6d9f598-2":{"type":"brand_image","settings":{"image":"shopify:\/\/shop_images\/03.png","link":"#"}},"1605783755d6d9f598-3":{"type":"brand_image","settings":{"image":"shopify:\/\/shop_images\/04.png","link":"#"}},"1605783755d6d9f598-4":{"type":"brand_image","settings":{"image":"shopify:\/\/shop_images\/05.png","link":"#"}},"1605783755d6d9f598-5":{"type":"brand_image","settings":{"image":"shopify:\/\/shop_images\/06.png","link":"#"}},"fe3f5195-5da5-4a16-b714-43fb3e5da4bd":{"type":"brand_image","settings":{"image":"shopify:\/\/shop_images\/07.png","link":"#"}}},"block_order":["1605783755d6d9f598-0","1605783755d6d9f598-1","1605783755d6d9f598-2","1605783755d6d9f598-3","1605783755d6d9f598-4","1605783755d6d9f598-5","fe3f5195-5da5-4a16-b714-43fb3e5da4bd"],"settings":{"addclass":"brands","bg_color":"#ffffff","title":"Shop By Brands","subtitle":"Over 1000+ Brands"}},"cms-subbanner":{"type":"cms-subbanner","settings":{"banner1_img":"shopify:\/\/shop_images\/banner-01.jpg","banner1_url":"","text1_position":"right","banner1_subtitle":"Big Deals","banner1_subtitle_color":"#111111","banner1_subtitle_bg_color":"#ffcc00","banner1_title":"Wireless Blue Xbox","banner1_title_color":"#ffffff","btn1_text":"","btn_link1":"","btn1_bg_color":"","btn1_txt_color":"","btn1_txt_hover_color":"","btn1_bg_hover_color":"","banner2_img":"shopify:\/\/shop_images\/banner-02.jpg","banner2_url":"","text2_position":"right","banner2_subtitle":"Redeem Coupon","banner2_subtitle_color":"#ffffff","banner2_title":"Beoplay h9i Limestone Headphone","banner2_title_color":"#ffffff","btn2_text":"Shop Now","btn_link2":"#","btn2_bg_color":"#ffffff","btn2_txt_color":"#111111","btn2_txt_hover_color":"#111111","btn2_bg_hover_color":"#ffcc00","banner3_img":"shopify:\/\/shop_images\/banner-03.jpg","banner3_url":"","text3_position":"right","banner3_subtitle":"Exclusive","banner3_subtitle_color":"#ffffff","banner3_title":"Home Speakers","banner3_title_color":"#ffffff","btn3_text":"Shop Now","btn_link3":"#","btn3_bg_color":"#ffffff","btn3_txt_color":"#111111","btn3_txt_hover_color":"#ffffff","btn3_bg_hover_color":"#2453c9"}},"product-tab-model":{"type":"product-tab-model","blocks":{"1595650811758-0":{"type":"text_block","settings":{"title":"New Products","collection":"laptop"}}},"block_order":["1595650811758-0"],"settings":{"product_rows":false,"product_col":"6","title":"Recently Arrived","subtitle":"Recently Arrived","button_text":"#666666","button_hover_text":"#111111","bg_color":"#f1ece8"}},"best-seller":{"type":"best-seller","settings":{"class":"bestproduct","product_rows":true,"title":"Bestsellers","subtitle":"Choose from best of selling items","collection":"electronics","product_col":"3"}},"cms-banner":{"type":"cms-banner","settings":{"banner1_img":"shopify:\/\/shop_images\/banner-04.jpg","banner1_url":"#","text1_position":"right","banner1_subtitle":"New Generation","banner1_subtitle_color":"#ffffff","banner1_title":"New Silicone Case Airpods 2","banner1_title_color":"#ffffff","btn1_text":"Shop Now","btn_link1":"#","btn1_bg_color":"#ffffff","btn1_txt_color":"#111111","btn1_txt_hover_color":"#111111","btn1_bg_hover_color":"#ffcc00","banner2_img":"shopify:\/\/shop_images\/banner-05.jpg","banner2_url":"#","text2_position":"right","banner2_subtitle":"New Generation","banner2_subtitle_color":"#ffffff","banner2_title":"Apple ipad Model Philippines","banner2_title_color":"#ffffff","btn2_text":"Shop Now","btn_link2":"#","btn2_bg_color":"#ffffff","btn2_txt_color":"#111111","btn2_txt_hover_color":"#111111","btn2_bg_hover_color":"#ffcc00"}},"category-slider":{"type":"category-slider","blocks":{"163333650951157a1a-0":{"type":"text_block","settings":{"title":"Electronics","banner_image":"shopify:\/\/shop_images\/category-banner-01.jpg","banner_image_link":"#","banner_title1":"Google Daydream","banner_btn_txt":"Shop Now","banner_title_clr1":"#111111","banner_btntxt_clr":"#ffffff","banner_btnbg_clr":"#111111","banner_btntxt_hvrclr":"#111111","banner_btnbg_hvrclr":"#ffffff","collection":"electronics"}},"3ef3388a-6574-4319-a3ff-cbe38846a771":{"type":"text_block","settings":{"title":"Speaker","banner_image":"shopify:\/\/shop_images\/category-banner-02.jpg","banner_image_link":"#","banner_title1":"Google Home Coloured","banner_btn_txt":"Shop Now","banner_title_clr1":"#ffffff","banner_btntxt_clr":"#ffffff","banner_btnbg_clr":"#111111","banner_btntxt_hvrclr":"#111111","banner_btnbg_hvrclr":"#ffffff","collection":"speaker"}},"ada20384-25e4-4006-b771-dc4473f51066":{"type":"text_block","settings":{"title":"Mobile","banner_image":"shopify:\/\/shop_images\/category-banner-03.jpg","banner_image_link":"","banner_title1":"New Genration Phone","banner_btn_txt":"Shop Now","banner_title_clr1":"#ffffff","banner_btntxt_clr":"#222222","banner_btnbg_clr":"#ffffff","banner_btntxt_hvrclr":"#111111","banner_btnbg_hvrclr":"#ffcc00","collection":"mobile"}},"ff669cf3-2070-4489-a31b-076fa2260f5f":{"type":"text_block","settings":{"title":"Kitchen","banner_image":"shopify:\/\/shop_images\/category-banner-04.jpg","banner_image_link":"#","banner_title1":"Kitchen & Appliances","banner_btn_txt":"Shop New","banner_title_clr1":"#ffffff","banner_btntxt_clr":"#ffffff","banner_btnbg_clr":"#111111","banner_btntxt_hvrclr":"#111111","banner_btnbg_hvrclr":"#ffffff","collection":"electronics1"}},"a0803d8b-0712-4140-b4f9-33deb2a597c2":{"type":"text_block","settings":{"title":"Furniture","banner_image":"shopify:\/\/shop_images\/category-banner-05.jpg","banner_image_link":"#","banner_title1":"Decorate Home Craft","banner_btn_txt":"Shop Now","banner_title_clr1":"#ffffff","banner_btntxt_clr":"#ffffff","banner_btnbg_clr":"#111111","banner_btntxt_hvrclr":"#111111","banner_btnbg_hvrclr":"#ffffff","collection":"furniture"}}},"block_order":["163333650951157a1a-0","3ef3388a-6574-4319-a3ff-cbe38846a771","ada20384-25e4-4006-b771-dc4473f51066","ff669cf3-2070-4489-a31b-076fa2260f5f","a0803d8b-0712-4140-b4f9-33deb2a597c2"],"settings":{"title":"Shop by Categories","subtitle":"Discover Best of Items","product_rows":false,"banner_display":true,"cat_product_col":"4","tab_clr":"#ffffff","tab_hvr_clr":"#ffcc00","heading_bg":"#23303e"}},"feature-blogs":{"type":"feature-blogs","settings":{"subtitle":"From the blog posts","subtitle_color":"#666666","title":"Latest News","blog":"electronics","blog_design":"design_1","product_col":"4","post_limit":"5","blog_btn_text":"#111111","blog_btn_hover_bg":"#2453c9","blog_hover_btn_text":"#ffffff","blog_date_color":"#ffffff","blog_bgdate_color":"#2453c9","show_view_all":false,"blog_show_date":true}},"16631550897b501cb1":{"type":"sticky-mobile-bar","settings":{"mobile_bar":true,"url_1":"https:\/\/themes-warehouse.myshopify.com\/","title_1":"Home","url_2":"shopify:\/\/collections","title_2":"Category","url_3":"https:\/\/themes-warehouse.myshopify.com\/cart","title_3":"Cart","url_4":"https:\/\/themes-warehouse.myshopify.com\/account\/login","title_4":"Account","url_5":"shopify:\/\/pages\/wishlist","title_5":"Wishlist"}}},"order":["cms-services","slideshow","top-category","tt-topoffer","special-product","category-feature","our_brand","cms-subbanner","product-tab-model","best-seller","cms-banner","category-slider","feature-blogs","16631550897b501cb1"]}